blanklibrary/__init__.py
blanklibrary/blanklibrary.py
blanklibrary-0.0.1.dist-info/METADATA
blanklibrary-0.0.1.dist-info/WHEEL
blanklibrary-0.0.1.dist-info/top_level.txt
blanklibrary-0.0.1.dist-info/RECORD
