Metadata-Version: 2.1
Name: blanklibrary
Version: 0.0.1
Summary: blanklibrary
Author: Flavko
Author-email: <flavio013568@gmail.com>
Classifier: Development Status :: 1 - Planning
Classifier: Intended Audience :: Developers
Classifier: Programming Language :: Python :: 3
Classifier: Operating System :: Unix
Classifier: Operating System :: MacOS :: MacOS X
Classifier: Operating System :: Microsoft :: Windows
